pyros_schemas/__init__.py
pyros_schemas/_version.py
pyros_schemas/ros/__init__.py
pyros_schemas/ros/basic_fields.py
pyros_schemas/ros/decorators.py
pyros_schemas/ros/exceptions.py
pyros_schemas/ros/optional_fields.py
pyros_schemas/ros/schema.py
pyros_schemas/ros/schemagic.py
pyros_schemas/ros/types_mapping.py
pyros_schemas/ros/utils.py
pyros_schemas/ros/schemas/__init__.py
pyros_schemas/ros/schemas/ros_std_msgs.py
pyros_schemas-0.1.0.dist-info/DESCRIPTION.rst
pyros_schemas-0.1.0.dist-info/METADATA
pyros_schemas-0.1.0.dist-info/RECORD
pyros_schemas-0.1.0.dist-info/WHEEL
pyros_schemas-0.1.0.dist-info/metadata.json
pyros_schemas-0.1.0.dist-info/pbr.json
pyros_schemas-0.1.0.dist-info/top_level.txt
