Metadata-Version: 2.0
Name: pyros-schemas
Version: 0.1.0
Summary: Pyros serialization
Home-page: http://github.com/asmodehn/pyros-schemas
Author: AlexV
Author-email: asmodehn@gmail.com
License: MIT
Platform: UNKNOWN
Requires-Dist: pyros-msgs (>=0.2.0)
Requires-Dist: six (>=1.5.2)
Requires-Dist: marshmallow (>=2.9.1)
